djadmin_rest2/__init__.py
djadmin_rest2/actions.py
djadmin_rest2/djadmin_hooks.py
djadmin_rest2/views.py
djadmin_rest2/templates/djadmin/icons/api.html
django_admin_deux_rest2-0.1.0.dist-info/licenses/LICENSE
django_admin_deux_rest2-0.1.0.dist-info/METADATA
django_admin_deux_rest2-0.1.0.dist-info/WHEEL
django_admin_deux_rest2-0.1.0.dist-info/entry_points.txt
django_admin_deux_rest2-0.1.0.dist-info/top_level.txt
django_admin_deux_rest2-0.1.0.dist-info/RECORD
