Metadata-Version: 2.4
Name: django-admin-deux-rest2
Version: 0.1.0
Summary: REST API plugin for django-admin-deux - Auto-generated RESTful endpoints for all ModelAdmins
Author: django-admin-deux contributors
License: MIT
Project-URL: Homepage, https://django-admin-deux.readthedocs.io/
Project-URL: Documentation, https://django-admin-deux.readthedocs.io/plugins/rest2/
Project-URL: Repository, https://codeberg.org/emmaDelescolle/django-admin-deux
Project-URL: Issues, https://codeberg.org/emmaDelescolle/django-admin-deux/issues
Project-URL: Changelog, https://codeberg.org/emmaDelescolle/django-admin-deux/releases
Keywords: django,admin,rest,api,rest-api,django-admin,plugin,crud
Classifier: Development Status :: 4 - Beta
Classifier: Framework :: Django
Classifier: Framework :: Django :: 5.2
Classifier: Framework :: Django :: 6.0
Classifier: Intended Audience :: Developers
Classifier: License :: OSI Approved :: MIT License
Classifier: Operating System :: OS Independent
Classifier: Programming Language :: Python
Classifier: Programming Language :: Python :: 3
Classifier: Programming Language :: Python :: 3.11
Classifier: Programming Language :: Python :: 3.12
Classifier: Programming Language :: Python :: 3.13
Classifier: Topic :: Internet :: WWW/HTTP
Classifier: Topic :: Software Development :: Libraries :: Python Modules
Requires-Python: >=3.11
License-File: LICENSE
Requires-Dist: django>=5.2
Requires-Dist: django-admin-deux>=0.1.0
Provides-Extra: dev
Requires-Dist: pytest>=8.0; extra == "dev"
Requires-Dist: pytest-django>=4.5; extra == "dev"
Requires-Dist: factory-boy>=3.3; extra == "dev"
Dynamic: license-file
